absolutely_nothing/__init__.py
absolutely_nothing/absolutely_nothing.py
absolutely_nothing-1.0.0.dist-info/LICENSE
absolutely_nothing-1.0.0.dist-info/WHEEL
absolutely_nothing-1.0.0.dist-info/METADATA
absolutely_nothing-1.0.0.dist-info/RECORD
