Metadata-Version: 2.1
Name: absolutely-nothing
Version: 1.0.0
Summary: A test module that does absolutely nothing.
Author: Zach Taira
Requires-Python: >=3.7.0,<4.0.0
Classifier: Programming Language :: Python :: 3
Classifier: Programming Language :: Python :: 3.10
Classifier: Programming Language :: Python :: 3.7
Classifier: Programming Language :: Python :: 3.8
Classifier: Programming Language :: Python :: 3.9
